{
  "sets": [
    {
      "name": "Starblock",
      "beltSlug": "yellow",
      "sets": [
        {
          "title": "SET 1: Starblock",
          "steps": [
            { "text": "Right Upward Block" },
            { "text": "Right Inward Block" },
            { "text": "Right Extended Outward Block" },
            { "text": "Right Downward Block" },
            { "text": "Right Inside Downward Block" },
            { "text": "Right Rear Elbow" },
            { "text": "Right Pushdown Block" },
            { "text": "Left Upward Block" },
            { "text": "Left Inward Block" },
            { "text": "Left Extended Outward Block" },
            { "text": "Left Downward Block" },
            { "text": "Left Inside Downward Block" },
            { "text": "Left Rear Elbow" },
            { "text": "Left Pushdown Block" }
          ]
        }
      ],
      "footerNotes": [
        "Executed from a horse stance, a neutral bow stance, and with a partner."
      ]
    }
  ]
}
